nox_ext/__init__.py
nox_ext/_nox_ext.py
nox_ext-0.3.1.dist-info/licenses/LICENSE
nox_ext-0.3.1.dist-info/METADATA
nox_ext-0.3.1.dist-info/WHEEL
nox_ext-0.3.1.dist-info/top_level.txt
nox_ext-0.3.1.dist-info/zip-safe
nox_ext-0.3.1.dist-info/RECORD
