Metadata-Version: 2.4
Name: nox_ext
Version: 0.3.1
Summary: Utility functions and helpers for Nox.
Author-email: Adam Karpierz <adam@karpierz.net>
Maintainer-email: Adam Karpierz <adam@karpierz.net>
License-Expression: Zlib
Project-URL: Homepage, https://pypi.org/project/nox-ext/
Project-URL: Documentation, https://karpierz.github.io/nox_ext/
Project-URL: History, https://karpierz.github.io/nox_ext/CHANGES.html
Project-URL: Download, https://pypi.org/project/nox-ext/
Project-URL: Repository, https://github.com/karpierz/nox_ext
Project-URL: Tracker, https://github.com/karpierz/nox_ext/issues
Project-URL: Sponsoring, https://www.paypal.com/donate/?hosted_button_id=FX8L7CJUGLW7S
Keywords: nox_ext,nox-ext,nox,packaging
Platform: any
Classifier: Development Status :: 5 - Production/Stable
Classifier: Intended Audience :: Developers
Classifier: Operating System :: OS Independent
Classifier: Natural Language :: Polish
Classifier: Programming Language :: Python
Classifier: Programming Language :: Python :: 3
Classifier: Programming Language :: Python :: 3.10
Classifier: Programming Language :: Python :: 3.11
Classifier: Programming Language :: Python :: 3.12
Classifier: Programming Language :: Python :: 3.13
Classifier: Programming Language :: Python :: 3.14
Classifier: Programming Language :: Python :: 3 :: Only
Classifier: Programming Language :: Python :: Implementation :: CPython
Classifier: Programming Language :: Python :: Implementation :: PyPy
Classifier: Topic :: Software Development :: Libraries :: Python Modules
Classifier: Typing :: Typed
Requires-Python: <4.0.0,>=3.10.2
License-File: LICENSE
Requires-Dist: typing-extensions>=4.15.0
Requires-Dist: packaging>=26.0.0
Requires-Dist: nox>=2025.11.12
Requires-Dist: build>=1.4.0
Requires-Dist: rich>=14.3.1
Dynamic: license-file
